Metadata-Version: 2.1
Name: RNAxtract
Version: 0.0.1
Summary: Splitting barcodes from RNA direct sequencing signals using Oxford Nanopore
Author: Lian Lin
Author-email: 21620151153308@stu.xmu.edu.cn
License: GPL3
Keywords: barcode split
